app_data/__init__.py
app_data/admin.py
app_data/containers.py
app_data/fields.py
app_data/forms.py
app_data/registry.py
django_appdata-0.4.0.dist-info/LICENSE
django_appdata-0.4.0.dist-info/METADATA
django_appdata-0.4.0.dist-info/WHEEL
django_appdata-0.4.0.dist-info/top_level.txt
django_appdata-0.4.0.dist-info/RECORD
