Metadata-Version: 2.1
Name: django-appdata
Version: 0.4.0
Summary: Extendable field that enables Django apps to store their data on your models.
Home-page: https://github.com/ella/django-appdata
Author: Ella Development Team
Author-email: dev@ellaproject.cz
License: BSD
Project-URL: Documentation, https://django-appdata.readthedocs.io/
Classifier: License :: OSI Approved :: BSD License
Classifier: Development Status :: 4 - Beta
Classifier: Framework :: Django
Classifier: Framework :: Django :: 3.2
Classifier: Framework :: Django :: 4.1
Classifier: Framework :: Django :: 4.2
Classifier: Programming Language :: Python
Classifier: Programming Language :: Python :: 3
Classifier: Programming Language :: Python :: 3.9
Classifier: Programming Language :: Python :: 3.10
Classifier: Programming Language :: Python :: 3.11
Classifier: Operating System :: OS Independent
Requires-Python: >=3.7
License-File: LICENSE
